CHANGELOG.rst
LICENSE
MANIFEST.in
NOTICE
README.rst
dependency-links.txt
requirements.txt
setup.py
pymodoro_i3blocks/__init__.py
pymodoro_i3blocks/pymodoro_i3blocks.py
pymodoro_i3blocks.egg-info/PKG-INFO
pymodoro_i3blocks.egg-info/SOURCES.txt
pymodoro_i3blocks.egg-info/dependency_links.txt
pymodoro_i3blocks.egg-info/entry_points.txt
pymodoro_i3blocks.egg-info/requires.txt
pymodoro_i3blocks.egg-info/top_level.txt