Metadata-Version: 1.1
Name: pymodoro-i3blocks
Version: 0.1.0
Summary: Displays and manages Pymodoro session states via i3blocks.
Home-page: https://github.com/toroettg/pymodoro-i3blocks
Author: Tobias Röttger
Author-email: dev@roettger-it.de
License: Apache License v2.0
Platform: any
Classifier: Development Status :: 4 - Beta
Classifier: Intended Audience :: End Users/Desktop
Classifier: License :: OSI Approved :: Apache Software License
Classifier: Operating System :: POSIX :: Linux
Classifier: Programming Language :: Python
Classifier: Programming Language :: Python :: 3
Classifier: Topic :: Utilities 
